goatfish/__init__.py
goatfish/models.py
goatfish/tests.py
goatfish-2.0.0a0.dist-info/WHEEL
goatfish-2.0.0a0.dist-info/METADATA
goatfish-2.0.0a0.dist-info/RECORD
