Metadata-Version: 2.1
Name: goatfish
Version: 2.0.0a0
Summary: A small, schemaless ORM that is backed by SQLite.
Home-page: https://github.com/stochastic-technologies/goatfish/
License: BSD-2-Clause
Keywords: database,schemaless,orm,sqlite
Author: Stavros Korokithakis
Author-email: hi@stavros.io
Requires-Python: >=3.4
Classifier: License :: OSI Approved :: BSD License
Classifier: Programming Language :: Python :: 3
Classifier: Programming Language :: Python :: 3.4
Classifier: Programming Language :: Python :: 3.5
Classifier: Programming Language :: Python :: 3.6
Classifier: Programming Language :: Python :: 3.7
Classifier: Programming Language :: Python :: 3.8
